torchist/__init__.py
torchist/histograms.py
torchist/metrics.py
torchist-1.0.1.dist-info/licenses/LICENSE
torchist-1.0.1.dist-info/METADATA
torchist-1.0.1.dist-info/WHEEL
torchist-1.0.1.dist-info/entry_points.txt
torchist-1.0.1.dist-info/top_level.txt
torchist-1.0.1.dist-info/RECORD
