Metadata-Version: 2.4
Name: torchist
Version: 1.0.1
Summary: NumPy-style histograms in PyTorch
Author-email: François Rozet <francois.rozet@outlook.com>
License-Expression: MIT
Project-URL: source, https://github.com/francois-rozet/torchist
Project-URL: tracker, https://github.com/francois-rozet/torchist/issues
Keywords: torch,histogram
Classifier: Intended Audience :: Developers
Classifier: Intended Audience :: Science/Research
Classifier: Natural Language :: English
Classifier: Operating System :: OS Independent
Classifier: Programming Language :: Python :: 3
Requires-Python: >=3.8
License-File: LICENSE
Requires-Dist: torch>=1.6.0
Provides-Extra: lint
Requires-Dist: ruff==0.9.9; extra == "lint"
Provides-Extra: test
Requires-Dist: numpy>=1.20.0; extra == "test"
Requires-Dist: pytest>=8.0.0; extra == "test"
Dynamic: license-file
